passwordgen/__init__.py
passwordgen/__main__.py
passwordgen/pattern.py
passwordgen/utils.py
passwordgen/worddict.py
passwordgen/words/words.txt
passwordgen/words/words.txt.old
passwordgen/words/defaults/english.txt
passwordgen/words/defaults/english_words.txt
passwordgen-0.2.data/data/LICENSE
passwordgen-0.2.data/data/README.rst
passwordgen-0.2.dist-info/DESCRIPTION.rst
passwordgen-0.2.dist-info/LICENSE.txt
passwordgen-0.2.dist-info/METADATA
passwordgen-0.2.dist-info/RECORD
passwordgen-0.2.dist-info/WHEEL
passwordgen-0.2.dist-info/entry_points.txt
passwordgen-0.2.dist-info/metadata.json
passwordgen-0.2.dist-info/top_level.txt
