Metadata-Version: 2.0
Name: passwordgen
Version: 0.2
Summary: A generator for safe and random passwords defined by a user-defined pattern
Home-page: https://github.com/nkrim/passwordgen
Author: Noah Krim
Author-email: nkrim62@gmail.com
License: MIT License
Keywords: passwordgen password generator safe random pattern
Platform: UNKNOWN
Classifier: Development Status :: 3 - Alpha
Classifier: Environment :: Console
Classifier: Intended Audience :: End Users/Desktop
Classifier: License :: OSI Approved :: MIT License
Classifier: Natural Language :: English
Classifier: Operating System :: OS Independent
Classifier: Programming Language :: Python
Classifier: Programming Language :: Python :: 2
Classifier: Programming Language :: Python :: 3
Classifier: Topic :: Security
Classifier: Topic :: Utilities
Requires-Dist: pyperclip (>=1.5.27)
